Metadata-Version: 2.1
Name: raft-dask-cu12
Version: 25.12.0
Summary: Reusable Accelerated Functions & Tools Dask Infrastructure
Author: NVIDIA Corporation
License: Apache-2.0
Classifier: Intended Audience :: Developers
Classifier: Programming Language :: Python
Classifier: Programming Language :: Python :: 3.10
Classifier: Programming Language :: Python :: 3.11
Classifier: Programming Language :: Python :: 3.12
Classifier: Programming Language :: Python :: 3.13
Project-URL: Homepage, https://github.com/rapidsai/raft
Project-URL: Documentation, https://docs.rapids.ai/api/raft/stable/
Requires-Python: >=3.10
Requires-Dist: dask-cuda==25.12.*
Requires-Dist: distributed-ucxx-cu12==0.47.*
Requires-Dist: libraft-cu12==25.12.*
Requires-Dist: nvidia-nccl-cu12>=2.19
Requires-Dist: pylibraft-cu12==25.12.*
Requires-Dist: rapids-dask-dependency==25.12.*
Provides-Extra: test
Requires-Dist: pytest-cov; extra == "test"
Requires-Dist: pytest<9.0.0a0; extra == "test"
